django_excel_response-2.0.1.dist-info/DESCRIPTION.rst
django_excel_response-2.0.1.dist-info/METADATA
django_excel_response-2.0.1.dist-info/RECORD
django_excel_response-2.0.1.dist-info/WHEEL
django_excel_response-2.0.1.dist-info/metadata.json
django_excel_response-2.0.1.dist-info/top_level.txt
excel_response/__init__.py
excel_response/response.py
excel_response/views.py
